hnet/__init__.py
hnet/adjmat_vec.py
hnet/examples.py
hnet/hnet.py
hnet/hnstats.py
hnet/network.py
hnet/savefig.py
hnet/gui/__init__.py
hnet/gui/hnet_gui.py
hnet/tests/test_hnet.py
hnet-1.3.0.dist-info/licenses/LICENCE.txt
hnet-1.3.0.dist-info/licenses/LICENSE
hnet-1.3.0.dist-info/METADATA
hnet-1.3.0.dist-info/WHEEL
hnet-1.3.0.dist-info/top_level.txt
hnet-1.3.0.dist-info/RECORD
