Metadata-Version: 2.4
Name: hnet
Version: 1.3.0
Summary: Graphical Hypergeometric Networks
Author-email: Erdogan Taskesen <erdogant@gmail.com>
License-Expression: MIT
Project-URL: Homepage, https://erdogant.github.io/hnet
Project-URL: Download, https://github.com/erdogant/hnet/archive/{version}.tar.gz
Keywords: Python,hnet,network analysis,tabular data,data analysis,graph,machine learning,AI
Classifier: Programming Language :: Python :: 3
Classifier: Intended Audience :: Education
Classifier: Intended Audience :: Science/Research
Classifier: Operating System :: Unix
Classifier: Operating System :: Microsoft :: Windows
Classifier: Operating System :: MacOS
Classifier: Operating System :: OS Independent
Classifier: Topic :: Scientific/Engineering :: Artificial Intelligence
Classifier: Topic :: Scientific/Engineering :: Bio-Informatics
Requires-Python: >=3
License-File: LICENCE.txt
License-File: LICENSE
Requires-Dist: colourmap
Requires-Dist: pypickle
Requires-Dist: classeval
Requires-Dist: matplotlib
Requires-Dist: numpy
Requires-Dist: pandas
Requires-Dist: statsmodels
Requires-Dist: networkx
Requires-Dist: python-louvain
Requires-Dist: tqdm
Requires-Dist: scikit-learn
Requires-Dist: ismember
Requires-Dist: imagesc
Requires-Dist: df2onehot
Requires-Dist: fsspec
Requires-Dist: datazets
Dynamic: license-file
